botocore/__init__.py
botocore/args.py
botocore/auth.py
botocore/awsrequest.py
botocore/cacert.pem
botocore/client.py
botocore/compat.py
botocore/compress.py
botocore/config.py
botocore/configloader.py
botocore/configprovider.py
botocore/credentials.py
botocore/discovery.py
botocore/endpoint.py
botocore/endpoint_provider.py
botocore/errorfactory.py
botocore/eventstream.py
botocore/exceptions.py
botocore/handlers.py
botocore/history.py
botocore/hooks.py
botocore/httpchecksum.py
botocore/httpsession.py
botocore/loaders.py
botocore/model.py
botocore/monitoring.py
botocore/paginate.py
botocore/parsers.py
botocore/regions.py
botocore/response.py
botocore/retryhandler.py
botocore/serialize.py
botocore/session.py
botocore/signers.py
botocore/stub.py
botocore/tokens.py
botocore/translate.py
botocore/useragent.py
botocore/utils.py
botocore/validate.py
botocore/waiter.py
botocore/crt/__init__.py
botocore/crt/auth.py
botocore/data/_retry.json
botocore/data/endpoints.json
botocore/data/partitions.json
botocore/data/sdk-default-configuration.json
botocore/data/accessanalyzer/2019-11-01/endpoint-rule-set-1.json.gz
botocore/data/accessanalyzer/2019-11-01/examples-1.json
botocore/data/accessanalyzer/2019-11-01/paginators-1.json
botocore/data/accessanalyzer/2019-11-01/paginators-1.sdk-extras.json
botocore/data/accessanalyzer/2019-11-01/service-2.json.gz
botocore/data/account/2021-02-01/endpoint-rule-set-1.json.gz
botocore/data/account/2021-02-01/examples-1.json
botocore/data/account/2021-02-01/paginators-1.json
botocore/data/account/2021-02-01/service-2.json.gz
botocore/data/acm/2015-12-08/endpoint-rule-set-1.json.gz
botocore/data/acm/2015-12-08/examples-1.json
botocore/data/acm/2015-12-08/paginators-1.json
botocore/data/acm/2015-12-08/service-2.json.gz
botocore/data/acm/2015-12-08/waiters-2.json
botocore/data/acm-pca/2017-08-22/endpoint-rule-set-1.json.gz
botocore/data/acm-pca/2017-08-22/examples-1.json
botocore/data/acm-pca/2017-08-22/paginators-1.json
botocore-1.35.73.dist-info/LICENSE.txt
botocore-1.35.73.dist-info/METADATA
botocore-1.35.73.dist-info/NOTICE
botocore-1.35.73.dist-info/WHEEL
botocore-1.35.73.dist-info/top_level.txt
botocore-1.35.73.dist-info/RECORD
