Metadata-Version: 2.1
Name: botocore
Version: 1.35.73
Summary: Low-level, data-driven core of boto 3.
Home-page: https://github.com/boto/botocore
Author: Amazon Web Services
License: Apache License 2.0
Classifier: Development Status :: 5 - Production/Stable
Classifier: Intended Audience :: Developers
Classifier: Intended Audience :: System Administrators
Classifier: Natural Language :: English
Classifier: License :: OSI Approved :: Apache Software License
Classifier: Programming Language :: Python
Classifier: Programming Language :: Python :: 3 :: Only
Classifier: Programming Language :: Python :: 3
Classifier: Programming Language :: Python :: 3.8
Classifier: Programming Language :: Python :: 3.9
Classifier: Programming Language :: Python :: 3.10
Classifier: Programming Language :: Python :: 3.11
Classifier: Programming Language :: Python :: 3.12
Classifier: Programming Language :: Python :: 3.13
Requires-Python: >= 3.8
License-File: LICENSE.txt
License-File: NOTICE
Requires-Dist: jmespath<2.0.0,>=0.7.1
Requires-Dist: python-dateutil<3.0.0,>=2.1
Requires-Dist: urllib3<1.27,>=1.25.4; python_version < "3.10"
Requires-Dist: urllib3!=2.2.0,<3,>=1.25.4; python_version >= "3.10"
Provides-Extra: crt
Requires-Dist: awscrt==0.22.0; extra == "crt"
